CHANGELOG.txt
COPYING
MANIFEST.in
README.txt
TODO.txt
build.sh
clean.sh
ez_setup.py
setup.py
doc/no-list.png
doc/ordered-list.png
doc/sample.html
doc/sample.mm
doc/skip-everything.png
doc/slide-build.png
doc/ui/default/blank.gif
doc/ui/default/bodybg.gif
doc/ui/default/framing.css
doc/ui/default/iepngfix.htc
doc/ui/default/opera.css
doc/ui/default/outline.css
doc/ui/default/pretty.css
doc/ui/default/print.css
doc/ui/default/s5-core.css
doc/ui/default/slides.css
doc/ui/default/slides.js
doc/ui/i18n/00_head.txt
doc/ui/i18n/bg-shade.png
doc/ui/i18n/bg-slide.jpg
doc/ui/i18n/framing.css
doc/ui/i18n/pretty.css
doc/ui/i18n/s5-core.css
doc/ui/i18n/slides.css
doc/ui/scott/blank.gif
doc/ui/scott/bodybg.gif
doc/ui/scott/bodybg.png
doc/ui/scott/framing.css
doc/ui/scott/iepngfix.htc
doc/ui/scott/opera.css
doc/ui/scott/outline.css
doc/ui/scott/pretty.css
doc/ui/scott/print.css
doc/ui/scott/s5-core.css
doc/ui/scott/scott.css
doc/ui/scott/slides.css
doc/ui/scott/slides.js
mm2s5/__init__.py
mm2s5/mm2s5.py
mm2s5.egg-info/PKG-INFO
mm2s5.egg-info/SOURCES.txt
mm2s5.egg-info/dependency_links.txt
mm2s5.egg-info/not-zip-safe
mm2s5.egg-info/top_level.txt
scripts/mm2s5