Metadata-Version: 1.0
Name: mm2s5
Version: 0.2.0
Summary: Convert a FreeMind mind-map (mm) into an S5 (html) presentation.
Home-page: http://code.google.com/mm2s5/
Author: Scott Kirkwood
Author-email: scottakirkwood@gmail.com
License: GNU GPL
Download-URL: http://mm2s5.googlecode.com/files/mm2s5-0.1.0.zip
Keywords: mm,S5,FreeMind,Presentation,XML,Python
Platform: POSIX
Platform: Windows
Classifier: Development Status :: 2 - Pre-Alpha
Classifier: Environment :: Console
Classifier: Intended Audience :: Developers
Classifier: Intended Audience :: Information Technology
Classifier: License :: OSI Approved :: GNU General Public License (GPL)
Classifier: Operating System :: OS Independent
Classifier: Operating System :: Microsoft :: Windows
Classifier: Operating System :: POSIX
Classifier: Programming Language :: Python
Classifier: Topic :: Database
Classifier: Topic :: Documentation
Classifier: Topic :: Software Development :: Code Generators
Classifier: Topic :: Text Processing :: Markup :: XML
Classifier: Topic :: Utilities
